Metadata-Version: 1.0
Name: splain
Version: 0.1
Summary: A module to explain Python exceptions as they occur.
Home-page: https://github.com/davidbpython/splain
Author: David Blaikie
Author-email: david@davidbpython.com
License: MIT
Platform: UNKNOWN
